{
  "openapi":"3.0.1",
  "info":{
    "title":"Clinica medica",
    "description":"API desenvolvida para clinica medica ",
    "version":"1"
  },
  "servers":[
    {
      "url":"http://localhost:8080",
      "description":"Generated server url"
    }
  ],
  "tags":[
    {
      "name":"Consulta",
      "description":"Rotas de consulta"
    }
  ],
  "paths":{
    "/consultas":{
      "get":{
        "tags":[
          "consulta-entity-controller"
        ],
        "description":"get-consulta",
        "operationId":"getCollectionResource-consulta-get_1",
        "parameters":[{
          "name":"page",
          "in":"query",
          "description":"Zero-based page index (0..N)",
          "required":false,
          "schema":{
            "minimum":0,
            "type":"integer",
            "default":0
          }
        },
          {
            "name":"size",
            "in":"query",
            "description":"The size of the page to be returned",
            "required":false,
            "schema":{
              "minimum":1,
              "type":"integer",
              "default":20}
          },{
            "name":"sort",
            "in":"query",
            "description":"Sorting criteria in the format: property,(asc|desc). Default sort order is ascending. Multiple sort criteria are supported.",
            "required":false,
            "schema":{
              "type":"array","items":{"type":"string"
              }
            }
          }
        ],
        "responses":{
          "200":{
            "description":"OK",
            "content":{
              "application/hal+json":{
                "schema":{
                  "$ref":"#/components/schemas/PagedModelEntityModelConsulta"
                }
              },
              "application/x-spring-data-compact+json":{
                "schema":{
                  "$ref":"#/components/schemas/PagedModelEntityModelConsulta"
                }
              },
              "text/uri-list":{
                "schema":{
                  "type":"string"
                }}
            }
          }
        }
      },
      "post":{"tags":["consulta-entity-controller"],"description":"create-consulta","operationId":"postCollectionResource-consulta-post","requestBody":{"content":{"application/json":{"schema":{"$ref":"#/components/schemas/ConsultaRequestBody"}}},"required":true},"responses":{"201":{"description":"Created","content":{"application/hal+json":{"schema":{"$ref":"#/components/schemas/EntityModelConsulta"}}}}}}},"/consultas/{id}":{"get":{"tags":["consulta-entity-controller"],"description":"get-consulta","operationId":"getItemResource-consulta-get","parameters":[{"name":"id","in":"path","required":true,"schema":{"type":"string"}}],"responses":{"200":{"description":"OK","content":{"application/hal+json":{"schema":{"$ref":"#/components/schemas/EntityModelConsulta"}}}},"404":{"description":"Not Found"}}},"put":{"tags":["consulta-entity-controller"],"description":"update-consulta","operationId":"putItemResource-consulta-put","parameters":[{"name":"id","in":"path","required":true,"schema":{"type":"string"}}],"requestBody":{"content":{"application/json":{"schema":{"$ref":"#/components/schemas/ConsultaRequestBody"}}},"required":true},"responses":{"200":{"description":"OK","content":{"application/hal+json":{"schema":{"$ref":"#/components/schemas/EntityModelConsulta"}}}},"201":{"description":"Created","content":{"application/hal+json":{"schema":{"$ref":"#/components/schemas/EntityModelConsulta"}}}},"204":{"description":"No Content"}}},"delete":{"tags":["consulta-entity-controller"],"description":"delete-consulta","operationId":"deleteItemResource-consulta-delete","parameters":[{"name":"id","in":"path","required":true,"schema":{"type":"string"}}],"responses":{"204":{"description":"No Content"},"404":{"description":"Not Found"}}},"patch":{"tags":["consulta-entity-controller"],"description":"patch-consulta","operationId":"patchItemResource-consulta-patch","parameters":[{"name":"id","in":"path","required":true,"schema":{"type":"string"}}],"requestBody":{"content":{"application/json":{"schema":{"$ref":"#/components/schemas/ConsultaRequestBody"}}},"required":true},"responses":{"200":{"description":"OK","content":{"application/hal+json":{"schema":{"$ref":"#/components/schemas/EntityModelConsulta"}}}},"204":{"description":"No Content"}}}},"/consultas/{id}/agenda":{"get":{"tags":["consulta-property-reference-controller"],"description":"get-schedule-by-consulta-Id","operationId":"followPropertyReference-consulta-get_1","parameters":[{"name":"id","in":"path","required":true,"schema":{"type":"string"}}],"responses":{"200":{"description":"OK","content":{"application/hal+json":{"schema":{"$ref":"#/components/schemas/CollectionModelSchedule"}},"text/uri-list":{"schema":{"type":"string"}}}},"404":{"description":"Not Found"}}},"put":{"tags":["consulta-property-reference-controller"],"description":"update-schedule-by-consulta-Id","operationId":"createPropertyReference-consulta-put","parameters":[{"name":"id","in":"path","required":true,"schema":{"type":"string"}}],"requestBody":{"content":{"application/json":{"schema":{"$ref":"#/components/schemas/CollectionModelObject"}},"application/x-spring-data-compact+json":{"schema":{"$ref":"#/components/schemas/CollectionModelObject"}},"text/uri-list":{"schema":{"type":"string"}}},"required":true},"responses":{"200":{"description":"OK","content":{"application/hal+json":{"schema":{"$ref":"#/components/schemas/CollectionModelSchedule"}}}},"201":{"description":"Created","content":{"application/hal+json":{"schema":{"$ref":"#/components/schemas/CollectionModelSchedule"}}}},"204":{"description":"No Content"}}},"delete":{"tags":["consulta-property-reference-controller"],"description":"delete-schedule-by-consulta-Id","operationId":"deletePropertyReference-consulta-delete","parameters":[{"name":"id","in":"path","required":true,"schema":{"type":"string"}}],"responses":{"204":{"description":"No Content"},"404":{"description":"Not Found"}}},"patch":{"tags":["consulta-property-reference-controller"],"description":"patch-schedule-by-consulta-Id","operationId":"createPropertyReference-consulta-patch","parameters":[{"name":"id","in":"path","required":true,"schema":{"type":"string"}}],"requestBody":{"content":{"application/json":{"schema":{"$ref":"#/components/schemas/CollectionModelObject"}},"application/x-spring-data-compact+json":{"schema":{"$ref":"#/components/schemas/CollectionModelObject"}},"text/uri-list":{"schema":{"type":"string"}}},"required":true},"responses":{"200":{"description":"OK","content":{"application/hal+json":{"schema":{"$ref":"#/components/schemas/CollectionModelSchedule"}}}},"204":{"description":"No Content"}}}},"/consultas/{id}/agenda/{propertyId}":{"get":{"tags":["consulta-property-reference-controller"],"description":"get-schedule-by-consulta-Id","operationId":"followPropertyReference-consulta-get","parameters":[{"name":"id","in":"path","required":true,"schema":{"type":"string"}},{"name":"propertyId","in":"path","required":true,"schema":{"type":"string"}}],"responses":{"200":{"description":"OK","content":{"application/hal+json":{"schema":{"$ref":"#/components/schemas/CollectionModelSchedule"}}}},"404":{"description":"Not Found"}}},"delete":{"tags":["consulta-property-reference-controller"],"description":"delete-schedule-by-consulta-Id","operationId":"deletePropertyReferenceId-consulta-delete","parameters":[{"name":"id","in":"path","required":true,"schema":{"type":"string"}},{"name":"propertyId","in":"path","required":true,"schema":{"type":"string"}}],"responses":{"204":{"description":"No Content"},"404":{"description":"Not Found"}}}},"/doctors":{"get":{"tags":["doctor-entity-controller","Doctor"],"summary":"Lista todos os medicos","description":"get-doctor","operationId":"getCollectionResource-doctor-get_1_1","parameters":[{"name":"page","in":"query","description":"Zero-based page index (0..N)","required":false,"schema":{"minimum":0,"type":"integer","default":0}},{"name":"size","in":"query","description":"The size of the page to be returned","required":false,"schema":{"minimum":1,"type":"integer","default":20}},{"name":"sort","in":"query","description":"Sorting criteria in the format: property,(asc|desc). Default sort order is ascending. Multiple sort criteria are supported.","required":false,"schema":{"type":"array","items":{"type":"string"}}}],"responses":{"404":{"description":"Not Found","content":{"application/hal+json":{"schema":{"type":"object","additionalProperties":{"type":"string"}}}}},"400":{"description":"Parametros inválidos","content":{"application/hal+json":{"schema":{"type":"object","additionalProperties":{"type":"string"}}}}},"422":{"description":"Dados de requisição inválida","content":{"application/hal+json":{"schema":{"type":"object","additionalProperties":{"type":"string"}}}}},"500":{"description":"Erro ao realizar busca dos dados","content":{"application/hal+json":{"schema":{"type":"object","additionalProperties":{"type":"string"}}}}},"405":{"description":"Method Not Allowed","content":{"application/hal+json":{"schema":{"type":"object","additionalProperties":{"type":"string"}}}}},"200":{"description":"Busca realizada com sucesso","content":{"application/hal+json":{"schema":{"$ref":"#/components/schemas/PagedModelEntityModelDoctor"}},"application/x-spring-data-compact+json":{"schema":{"$ref":"#/components/schemas/PagedModelEntityModelDoctor"}},"text/uri-list":{"schema":{"type":"string"}}}}}},"post":{"tags":["doctor-entity-controller","Doctor"],"summary":"Cadastra novo doctor","description":"create-doctor","operationId":"postCollectionResource-doctor-post_1","requestBody":{"content":{"application/json":{"schema":{"$ref":"#/components/schemas/Doctor"}}},"required":true},"responses":{"404":{"description":"Not Found","content":{"application/hal+json":{"schema":{"type":"object","additionalProperties":{"type":"string"}}}}},"400":{"description":"Parametros inválidos","content":{"application/hal+json":{"schema":{"type":"object","additionalProperties":{"type":"string"}}}}},"422":{"description":"Dados de requisição inválida","content":{"application/hal+json":{"schema":{"type":"object","additionalProperties":{"type":"string"}}}}},"500":{"description":"Erro ao realizar busca dos dados","content":{"application/hal+json":{"schema":{"type":"object","additionalProperties":{"type":"string"}}}}},"405":{"description":"Method Not Allowed","content":{"application/hal+json":{"schema":{"type":"object","additionalProperties":{"type":"string"}}}}},"201":{"description":"Created","content":{"application/hal+json":{"schema":{"$ref":"#/components/schemas/EntityModelDoctor"}}}},"200":{"description":"Busca realizada com sucesso","content":{"application/hal+json":{"schema":{"$ref":"#/components/schemas/Doctor"}}}}}}},"/doctors/{id}":{"get":{"tags":["doctor-entity-controller","Doctor"],"summary":"Lista doctor especifico","description":"get-doctor","operationId":"getItemResource-doctor-get_1","parameters":[{"name":"id","in":"path","required":true,"schema":{"type":"string"}}],"responses":{"404":{"description":"Not Found"},"400":{"description":"Parametros inválidos","content":{"application/hal+json":{"schema":{"type":"object","additionalProperties":{"type":"string"}}}}},"422":{"description":"Dados de requisição inválida","content":{"application/hal+json":{"schema":{"type":"object","additionalProperties":{"type":"string"}}}}},"500":{"description":"Erro ao realizar busca dos dados","content":{"application/hal+json":{"schema":{"type":"object","additionalProperties":{"type":"string"}}}}},"405":{"description":"Method Not Allowed","content":{"application/hal+json":{"schema":{"type":"object","additionalProperties":{"type":"string"}}}}},"200":{"description":"Busca realizada com sucesso","content":{"application/hal+json":{"schema":{"$ref":"#/components/schemas/EntityModelDoctor"}}}}}},"put":{"tags":["doctor-entity-controller","Doctor"],"summary":"Atualiza os dados do doctor","description":"update-doctor","operationId":"putItemResource-doctor-put_1","parameters":[{"name":"id","in":"path","required":true,"schema":{"type":"string"}}],"requestBody":{"content":{"application/json":{"schema":{"$ref":"#/components/schemas/Doctor"}}},"required":true},"responses":{"404":{"description":"Not Found","content":{"application/hal+json":{"schema":{"type":"object","additionalProperties":{"type":"string"}}}}},"400":{"description":"Parametros inválidos","content":{"application/hal+json":{"schema":{"type":"object","additionalProperties":{"type":"string"}}}}},"422":{"description":"Dados de requisição inválida","content":{"application/hal+json":{"schema":{"type":"object","additionalProperties":{"type":"string"}}}}},"500":{"description":"Erro ao realizar busca dos dados","content":{"application/hal+json":{"schema":{"type":"object","additionalProperties":{"type":"string"}}}}},"405":{"description":"Method Not Allowed","content":{"application/hal+json":{"schema":{"type":"object","additionalProperties":{"type":"string"}}}}},"200":{"description":"OK","content":{"application/hal+json":{"schema":{"$ref":"#/components/schemas/EntityModelDoctor"}}}},"201":{"description":"Created","content":{"application/hal+json":{"schema":{"$ref":"#/components/schemas/EntityModelDoctor"}}}},"204":{"description":"Busca realizada com sucesso","content":{"application/hal+json":{"schema":{"$ref":"#/components/schemas/Doctor"}}}}}},"delete":{"tags":["doctor-entity-controller","Doctor"],"summary":"Deleta doctor","description":"delete-doctor","operationId":"deleteItemResource-doctor-delete_1","parameters":[{"name":"id","in":"path","required":true,"schema":{"type":"string"}}],"responses":{"404":{"description":"Not Found"},"400":{"description":"Parametros inválidos","content":{"application/hal+json":{"schema":{"type":"object","additionalProperties":{"type":"string"}}}}},"422":{"description":"Dados de requisição inválida","content":{"application/hal+json":{"schema":{"type":"object","additionalProperties":{"type":"string"}}}}},"500":{"description":"Erro ao realizar busca dos dados","content":{"application/hal+json":{"schema":{"type":"object","additionalProperties":{"type":"string"}}}}},"405":{"description":"Method Not Allowed","content":{"application/hal+json":{"schema":{"type":"object","additionalProperties":{"type":"string"}}}}},"204":{"description":"No Content"},"200":{"description":"Busca realizada com sucesso","content":{"application/hal+json":{"schema":{"type":"string"}}}}}},"patch":{"tags":["doctor-entity-controller"],"description":"patch-doctor","operationId":"patchItemResource-doctor-patch","parameters":[{"name":"id","in":"path","required":true,"schema":{"type":"string"}}],"requestBody":{"content":{"application/json":{"schema":{"$ref":"#/components/schemas/DoctorRequestBody"}}},"required":true},"responses":{"200":{"description":"OK","content":{"application/hal+json":{"schema":{"$ref":"#/components/schemas/EntityModelDoctor"}}}},"204":{"description":"No Content"}}}},"/doctors/{id}/schedules":{"get":{"tags":["doctor-property-reference-controller"],"description":"get-schedule-by-doctor-Id","operationId":"followPropertyReference-doctor-get_1","parameters":[{"name":"id","in":"path","required":true,"schema":{"type":"string"}}],"responses":{"200":{"description":"OK","content":{"application/hal+json":{"schema":{"$ref":"#/components/schemas/CollectionModelSchedule"}},"text/uri-list":{"schema":{"type":"string"}}}},"404":{"description":"Not Found"}}},"put":{"tags":["doctor-property-reference-controller"],"description":"update-schedule-by-doctor-Id","operationId":"createPropertyReference-doctor-put","parameters":[{"name":"id","in":"path","required":true,"schema":{"type":"string"}}],"requestBody":{"content":{"application/json":{"schema":{"$ref":"#/components/schemas/CollectionModelObject"}},"application/x-spring-data-compact+json":{"schema":{"$ref":"#/components/schemas/CollectionModelObject"}},"text/uri-list":{"schema":{"type":"string"}}},"required":true},"responses":{"200":{"description":"OK","content":{"application/hal+json":{"schema":{"$ref":"#/components/schemas/CollectionModelSchedule"}}}},"201":{"description":"Created","content":{"application/hal+json":{"schema":{"$ref":"#/components/schemas/CollectionModelSchedule"}}}},"204":{"description":"No Content"}}},"delete":{"tags":["doctor-property-reference-controller"],"description":"delete-schedule-by-doctor-Id","operationId":"deletePropertyReference-doctor-delete","parameters":[{"name":"id","in":"path","required":true,"schema":{"type":"string"}}],"responses":{"204":{"description":"No Content"},"404":{"description":"Not Found"}}},"patch":{"tags":["doctor-property-reference-controller"],"description":"patch-schedule-by-doctor-Id","operationId":"createPropertyReference-doctor-patch","parameters":[{"name":"id","in":"path","required":true,"schema":{"type":"string"}}],"requestBody":{"content":{"application/json":{"schema":{"$ref":"#/components/schemas/CollectionModelObject"}},"application/x-spring-data-compact+json":{"schema":{"$ref":"#/components/schemas/CollectionModelObject"}},"text/uri-list":{"schema":{"type":"string"}}},"required":true},"responses":{"200":{"description":"OK","content":{"application/hal+json":{"schema":{"$ref":"#/components/schemas/CollectionModelSchedule"}}}},"204":{"description":"No Content"}}}},"/doctors/{id}/schedules/{propertyId}":{"get":{"tags":["doctor-property-reference-controller"],"description":"get-schedule-by-doctor-Id","operationId":"followPropertyReference-doctor-get","parameters":[{"name":"id","in":"path","required":true,"schema":{"type":"string"}},{"name":"propertyId","in":"path","required":true,"schema":{"type":"string"}}],"responses":{"200":{"description":"OK","content":{"application/hal+json":{"schema":{"$ref":"#/components/schemas/CollectionModelSchedule"}}}},"404":{"description":"Not Found"}}},"delete":{"tags":["doctor-property-reference-controller"],"description":"delete-schedule-by-doctor-Id","operationId":"deletePropertyReferenceId-doctor-delete","parameters":[{"name":"id","in":"path","required":true,"schema":{"type":"string"}},{"name":"propertyId","in":"path","required":true,"schema":{"type":"string"}}],"responses":{"204":{"description":"No Content"},"404":{"description":"Not Found"}}}},"/exams":{"get":{"tags":["exam-entity-controller"],"description":"get-exam","operationId":"getCollectionResource-exam-get_1","parameters":[{"name":"page","in":"query","description":"Zero-based page index (0..N)","required":false,"schema":{"minimum":0,"type":"integer","default":0}},{"name":"size","in":"query","description":"The size of the page to be returned","required":false,"schema":{"minimum":1,"type":"integer","default":20}},{"name":"sort","in":"query","description":"Sorting criteria in the format: property,(asc|desc). Default sort order is ascending. Multiple sort criteria are supported.","required":false,"schema":{"type":"array","items":{"type":"string"}}}],"responses":{"200":{"description":"OK","content":{"application/hal+json":{"schema":{"$ref":"#/components/schemas/PagedModelEntityModelExam"}},"application/x-spring-data-compact+json":{"schema":{"$ref":"#/components/schemas/PagedModelEntityModelExam"}},"text/uri-list":{"schema":{"type":"string"}}}}}},"post":{"tags":["exam-entity-controller"],"description":"create-exam","operationId":"postCollectionResource-exam-post","requestBody":{"content":{"application/json":{"schema":{"$ref":"#/components/schemas/ExamRequestBody"}}},"required":true},"responses":{"201":{"description":"Created","content":{"application/hal+json":{"schema":{"$ref":"#/components/schemas/EntityModelExam"}}}}}}},"/exams/{id}":{"get":{"tags":["exam-entity-controller"],"description":"get-exam","operationId":"getItemResource-exam-get","parameters":[{"name":"id","in":"path","required":true,"schema":{"type":"string"}}],"responses":{"200":{"description":"OK","content":{"application/hal+json":{"schema":{"$ref":"#/components/schemas/EntityModelExam"}}}},"404":{"description":"Not Found"}}},"put":{"tags":["exam-entity-controller"],"description":"update-exam","operationId":"putItemResource-exam-put","parameters":[{"name":"id","in":"path","required":true,"schema":{"type":"string"}}],"requestBody":{"content":{"application/json":{"schema":{"$ref":"#/components/schemas/ExamRequestBody"}}},"required":true},"responses":{"200":{"description":"OK","content":{"application/hal+json":{"schema":{"$ref":"#/components/schemas/EntityModelExam"}}}},"201":{"description":"Created","content":{"application/hal+json":{"schema":{"$ref":"#/components/schemas/EntityModelExam"}}}},"204":{"description":"No Content"}}},"delete":{"tags":["exam-entity-controller"],"description":"delete-exam","operationId":"deleteItemResource-exam-delete","parameters":[{"name":"id","in":"path","required":true,"schema":{"type":"string"}}],"responses":{"204":{"description":"No Content"},"404":{"description":"Not Found"}}},"patch":{"tags":["exam-entity-controller"],"description":"patch-exam","operationId":"patchItemResource-exam-patch","parameters":[{"name":"id","in":"path","required":true,"schema":{"type":"string"}}],"requestBody":{"content":{"application/json":{"schema":{"$ref":"#/components/schemas/ExamRequestBody"}}},"required":true},"responses":{"200":{"description":"OK","content":{"application/hal+json":{"schema":{"$ref":"#/components/schemas/EntityModelExam"}}}},"204":{"description":"No Content"}}}},"/pacientes":{"get":{"tags":["paciente-entity-controller"],"description":"get-paciente","operationId":"getCollectionResource-paciente-get_1","parameters":[{"name":"page","in":"query","description":"Zero-based page index (0..N)","required":false,"schema":{"minimum":0,"type":"integer","default":0}},{"name":"size","in":"query","description":"The size of the page to be returned","required":false,"schema":{"minimum":1,"type":"integer","default":20}},{"name":"sort","in":"query","description":"Sorting criteria in the format: property,(asc|desc). Default sort order is ascending. Multiple sort criteria are supported.","required":false,"schema":{"type":"array","items":{"type":"string"}}}],"responses":{"200":{"description":"OK","content":{"application/hal+json":{"schema":{"$ref":"#/components/schemas/PagedModelEntityModelPaciente"}},"application/x-spring-data-compact+json":{"schema":{"$ref":"#/components/schemas/PagedModelEntityModelPaciente"}},"text/uri-list":{"schema":{"type":"string"}}}}}},"post":{"tags":["paciente-entity-controller"],"description":"create-paciente","operationId":"postCollectionResource-paciente-post","requestBody":{"content":{"application/json":{"schema":{"$ref":"#/components/schemas/PacienteRequestBody"}}},"required":true},"responses":{"201":{"description":"Created","content":{"application/hal+json":{"schema":{"$ref":"#/components/schemas/EntityModelPaciente"}}}}}}},"/pacientes/{id}":{"get":{"tags":["paciente-entity-controller"],"description":"get-paciente","operationId":"getItemResource-paciente-get","parameters":[{"name":"id","in":"path","required":true,"schema":{"type":"string"}}],"responses":{"200":{"description":"OK","content":{"application/hal+json":{"schema":{"$ref":"#/components/schemas/EntityModelPaciente"}}}},"404":{"description":"Not Found"}}},"put":{"tags":["paciente-entity-controller"],"description":"update-paciente","operationId":"putItemResource-paciente-put","parameters":[{"name":"id","in":"path","required":true,"schema":{"type":"string"}}],"requestBody":{"content":{"application/json":{"schema":{"$ref":"#/components/schemas/PacienteRequestBody"}}},"required":true},"responses":{"200":{"description":"OK","content":{"application/hal+json":{"schema":{"$ref":"#/components/schemas/EntityModelPaciente"}}}},"201":{"description":"Created","content":{"application/hal+json":{"schema":{"$ref":"#/components/schemas/EntityModelPaciente"}}}},"204":{"description":"No Content"}}},"delete":{"tags":["paciente-entity-controller"],"description":"delete-paciente","operationId":"deleteItemResource-paciente-delete","parameters":[{"name":"id","in":"path","required":true,"schema":{"type":"string"}}],"responses":{"204":{"description":"No Content"},"404":{"description":"Not Found"}}},"patch":{"tags":["paciente-entity-controller"],"description":"patch-paciente","operationId":"patchItemResource-paciente-patch","parameters":[{"name":"id","in":"path","required":true,"schema":{"type":"string"}}],"requestBody":{"content":{"application/json":{"schema":{"$ref":"#/components/schemas/PacienteRequestBody"}}},"required":true},"responses":{"200":{"description":"OK","content":{"application/hal+json":{"schema":{"$ref":"#/components/schemas/EntityModelPaciente"}}}},"204":{"description":"No Content"}}}},"/profile":{"get":{"tags":["profile-controller"],"operationId":"listAllFormsOfMetadata_1","responses":{"200":{"description":"OK","content":{"application/hal+json":{"schema":{"$ref":"#/components/schemas/RepresentationModelObject"}}}}}}},"/profile/consultas":{"get":{"tags":["profile-controller"],"operationId":"descriptor_1_1_1","responses":{"200":{"description":"OK","content":{"*/*":{"schema":{"type":"string"}},"application/alps+json":{"schema":{"type":"string"}},"application/schema+json":{"schema":{"$ref":"#/components/schemas/JsonSchema"}}}}}}},"/profile/doctors":{"get":{"tags":["profile-controller"],"operationId":"descriptor_1_1_2","responses":{"200":{"description":"OK","content":{"*/*":{"schema":{"type":"string"}},"application/alps+json":{"schema":{"type":"string"}},"application/schema+json":{"schema":{"$ref":"#/components/schemas/JsonSchema"}}}}}}},"/profile/exams":{"get":{"tags":["profile-controller"],"operationId":"descriptor_1_1_3","responses":{"200":{"description":"OK","content":{"*/*":{"schema":{"type":"string"}},"application/alps+json":{"schema":{"type":"string"}},"application/schema+json":{"schema":{"$ref":"#/components/schemas/JsonSchema"}}}}}}},"/profile/pacientes":{"get":{"tags":["profile-controller"],"operationId":"descriptor_1_1_4","responses":{"200":{"description":"OK","content":{"*/*":{"schema":{"type":"string"}},"application/alps+json":{"schema":{"type":"string"}},"application/schema+json":{"schema":{"$ref":"#/components/schemas/JsonSchema"}}}}}}},"/profile/responsavels":{"get":{"tags":["profile-controller"],"operationId":"descriptor_1_1_5","responses":{"200":{"description":"OK","content":{"*/*":{"schema":{"type":"string"}},"application/alps+json":{"schema":{"type":"string"}},"application/schema+json":{"schema":{"$ref":"#/components/schemas/JsonSchema"}}}}}}},"/profile/schedules":{"get":{"tags":["profile-controller"],"operationId":"descriptor_1_1_6","responses":{"200":{"description":"OK","content":{"*/*":{"schema":{"type":"string"}},"application/alps+json":{"schema":{"type":"string"}},"application/schema+json":{"schema":{"$ref":"#/components/schemas/JsonSchema"}}}}}}},"/responsavels":{"get":{"tags":["responsavel-entity-controller"],"description":"get-responsavel","operationId":"getCollectionResource-responsavel-get_1","parameters":[{"name":"page","in":"query","description":"Zero-based page index (0..N)","required":false,"schema":{"minimum":0,"type":"integer","default":0}},{"name":"size","in":"query","description":"The size of the page to be returned","required":false,"schema":{"minimum":1,"type":"integer","default":20}},{"name":"sort","in":"query","description":"Sorting criteria in the format: property,(asc|desc). Default sort order is ascending. Multiple sort criteria are supported.","required":false,"schema":{"type":"array","items":{"type":"string"}}}],"responses":{"200":{"description":"OK","content":{"application/hal+json":{"schema":{"$ref":"#/components/schemas/PagedModelEntityModelResponsavel"}},"application/x-spring-data-compact+json":{"schema":{"$ref":"#/components/schemas/PagedModelEntityModelResponsavel"}},"text/uri-list":{"schema":{"type":"string"}}}}}},"post":{"tags":["responsavel-entity-controller"],"description":"create-responsavel","operationId":"postCollectionResource-responsavel-post","requestBody":{"content":{"application/json":{"schema":{"$ref":"#/components/schemas/ResponsavelRequestBody"}}},"required":true},"responses":{"201":{"description":"Created","content":{"application/hal+json":{"schema":{"$ref":"#/components/schemas/EntityModelResponsavel"}}}}}}},"/responsavels/{id}":{"get":{"tags":["responsavel-entity-controller"],"description":"get-responsavel","operationId":"getItemResource-responsavel-get","parameters":[{"name":"id","in":"path","required":true,"schema":{"type":"string"}}],"responses":{"200":{"description":"OK","content":{"application/hal+json":{"schema":{"$ref":"#/components/schemas/EntityModelResponsavel"}}}},"404":{"description":"Not Found"}}},"put":{"tags":["responsavel-entity-controller"],"description":"update-responsavel","operationId":"putItemResource-responsavel-put","parameters":[{"name":"id","in":"path","required":true,"schema":{"type":"string"}}],"requestBody":{"content":{"application/json":{"schema":{"$ref":"#/components/schemas/ResponsavelRequestBody"}}},"required":true},"responses":{"200":{"description":"OK","content":{"application/hal+json":{"schema":{"$ref":"#/components/schemas/EntityModelResponsavel"}}}},"201":{"description":"Created","content":{"application/hal+json":{"schema":{"$ref":"#/components/schemas/EntityModelResponsavel"}}}},"204":{"description":"No Content"}}},"delete":{"tags":["responsavel-entity-controller"],"description":"delete-responsavel","operationId":"deleteItemResource-responsavel-delete","parameters":[{"name":"id","in":"path","required":true,"schema":{"type":"string"}}],"responses":{"204":{"description":"No Content"},"404":{"description":"Not Found"}}},"patch":{"tags":["responsavel-entity-controller"],"description":"patch-responsavel","operationId":"patchItemResource-responsavel-patch","parameters":[{"name":"id","in":"path","required":true,"schema":{"type":"string"}}],"requestBody":{"content":{"application/json":{"schema":{"$ref":"#/components/schemas/ResponsavelRequestBody"}}},"required":true},"responses":{"200":{"description":"OK","content":{"application/hal+json":{"schema":{"$ref":"#/components/schemas/EntityModelResponsavel"}}}},"204":{"description":"No Content"}}}},"/schedules":{"get":{"tags":["schedule-entity-controller"],"description":"get-schedule","operationId":"getCollectionResource-schedule-get_1","parameters":[{"name":"page","in":"query","description":"Zero-based page index (0..N)","required":false,"schema":{"minimum":0,"type":"integer","default":0}},{"name":"size","in":"query","description":"The size of the page to be returned","required":false,"schema":{"minimum":1,"type":"integer","default":20}},{"name":"sort","in":"query","description":"Sorting criteria in the format: property,(asc|desc). Default sort order is ascending. Multiple sort criteria are supported.","required":false,"schema":{"type":"array","items":{"type":"string"}}}],"responses":{"200":{"description":"OK","content":{"application/hal+json":{"schema":{"$ref":"#/components/schemas/PagedModelEntityModelSchedule"}},"application/x-spring-data-compact+json":{"schema":{"$ref":"#/components/schemas/PagedModelEntityModelSchedule"}},"text/uri-list":{"schema":{"type":"string"}}}}}},"post":{"tags":["Schedule","schedule-entity-controller"],"summary":"Busca dados de profissionais por idade e cargo exercido","description":"create-schedule","operationId":"postCollectionResource-schedule-post_1","requestBody":{"content":{"application/json":{"schema":{"$ref":"#/components/schemas/Schedule"}}},"required":true},"responses":{"404":{"description":"Not Found","content":{"application/hal+json":{"schema":{"type":"object","additionalProperties":{"type":"string"}}}}},"400":{"description":"Parametros inválidos","content":{"application/hal+json":{"schema":{"type":"object","additionalProperties":{"type":"string"}}}}},"422":{"description":"Dados de requisição inválida","content":{"application/hal+json":{"schema":{"type":"object","additionalProperties":{"type":"string"}}}}},"500":{"description":"Erro ao realizar busca dos dados","content":{"application/hal+json":{"schema":{"type":"object","additionalProperties":{"type":"string"}}}}},"405":{"description":"Method Not Allowed","content":{"application/hal+json":{"schema":{"type":"object","additionalProperties":{"type":"string"}}}}},"201":{"description":"Created","content":{"application/hal+json":{"schema":{"$ref":"#/components/schemas/EntityModelSchedule"}}}},"200":{"description":"Busca realizada com sucesso","content":{"application/json":{"schema":{"$ref":"#/components/schemas/Schedule"}}}}}}},"/schedules/{id}":{"get":{"tags":["schedule-entity-controller"],"description":"get-schedule","operationId":"getItemResource-schedule-get","parameters":[{"name":"id","in":"path","required":true,"schema":{"type":"string"}}],"responses":{"200":{"description":"OK","content":{"application/hal+json":{"schema":{"$ref":"#/components/schemas/EntityModelSchedule"}}}},"404":{"description":"Not Found"}}},"put":{"tags":["schedule-entity-controller"],"description":"update-schedule","operationId":"putItemResource-schedule-put","parameters":[{"name":"id","in":"path","required":true,"schema":{"type":"string"}}],"requestBody":{"content":{"application/json":{"schema":{"$ref":"#/components/schemas/ScheduleRequestBody"}}},"required":true},"responses":{"200":{"description":"OK","content":{"application/hal+json":{"schema":{"$ref":"#/components/schemas/EntityModelSchedule"}}}},"201":{"description":"Created","content":{"application/hal+json":{"schema":{"$ref":"#/components/schemas/EntityModelSchedule"}}}},"204":{"description":"No Content"}}},"delete":{"tags":["schedule-entity-controller"],"description":"delete-schedule","operationId":"deleteItemResource-schedule-delete","parameters":[{"name":"id","in":"path","required":true,"schema":{"type":"string"}}],"responses":{"204":{"description":"No Content"},"404":{"description":"Not Found"}}},"patch":{"tags":["schedule-entity-controller"],"description":"patch-schedule","operationId":"patchItemResource-schedule-patch","parameters":[{"name":"id","in":"path","required":true,"schema":{"type":"string"}}],"requestBody":{"content":{"application/json":{"schema":{"$ref":"#/components/schemas/ScheduleRequestBody"}}},"required":true},"responses":{"200":{"description":"OK","content":{"application/hal+json":{"schema":{"$ref":"#/components/schemas/EntityModelSchedule"}}}},"204":{"description":"No Content"}}}},"/schedules/{id}/consulta":{"get":{"tags":["schedule-property-reference-controller"],"description":"get-consulta-by-schedule-Id","operationId":"followPropertyReference-schedule-get_1","parameters":[{"name":"id","in":"path","required":true,"schema":{"type":"string"}}],"responses":{"200":{"description":"OK","content":{"application/hal+json":{"schema":{"$ref":"#/components/schemas/EntityModelConsulta"}},"text/uri-list":{"schema":{"type":"string"}}}},"404":{"description":"Not Found"}}},"put":{"tags":["schedule-property-reference-controller"],"description":"update-consulta-by-schedule-Id","operationId":"createPropertyReference-schedule-put","parameters":[{"name":"id","in":"path","required":true,"schema":{"type":"string"}}],"requestBody":{"content":{"application/json":{"schema":{"$ref":"#/components/schemas/CollectionModelObject"}},"application/x-spring-data-compact+json":{"schema":{"$ref":"#/components/schemas/CollectionModelObject"}},"text/uri-list":{"schema":{"type":"string"}}},"required":true},"responses":{"200":{"description":"OK","content":{"application/hal+json":{"schema":{"$ref":"#/components/schemas/EntityModelConsulta"}}}},"201":{"description":"Created","content":{"application/hal+json":{"schema":{"$ref":"#/components/schemas/EntityModelConsulta"}}}},"204":{"description":"No Content"}}},"delete":{"tags":["schedule-property-reference-controller"],"description":"delete-consulta-by-schedule-Id","operationId":"deletePropertyReference-schedule-delete","parameters":[{"name":"id","in":"path","required":true,"schema":{"type":"string"}}],"responses":{"204":{"description":"No Content"},"404":{"description":"Not Found"}}},"patch":{"tags":["schedule-property-reference-controller"],"description":"patch-consulta-by-schedule-Id","operationId":"createPropertyReference-schedule-patch","parameters":[{"name":"id","in":"path","required":true,"schema":{"type":"string"}}],"requestBody":{"content":{"application/json":{"schema":{"$ref":"#/components/schemas/CollectionModelObject"}},"application/x-spring-data-compact+json":{"schema":{"$ref":"#/components/schemas/CollectionModelObject"}},"text/uri-list":{"schema":{"type":"string"}}},"required":true},"responses":{"200":{"description":"OK","content":{"application/hal+json":{"schema":{"$ref":"#/components/schemas/EntityModelConsulta"}}}},"204":{"description":"No Content"}}}},"/schedules/{id}/consulta/{propertyId}":{"get":{"tags":["schedule-property-reference-controller"],"description":"get-consulta-by-schedule-Id","operationId":"followPropertyReference-schedule-get","parameters":[{"name":"id","in":"path","required":true,"schema":{"type":"string"}},{"name":"propertyId","in":"path","required":true,"schema":{"type":"string"}}],"responses":{"200":{"description":"OK","content":{"application/hal+json":{"schema":{"$ref":"#/components/schemas/EntityModelConsulta"}}}},"404":{"description":"Not Found"}}},"delete":{"tags":["schedule-property-reference-controller"],"description":"delete-consulta-by-schedule-Id","operationId":"deletePropertyReferenceId-schedule-delete","parameters":[{"name":"id","in":"path","required":true,"schema":{"type":"string"}},{"name":"propertyId","in":"path","required":true,"schema":{"type":"string"}}],"responses":{"204":{"description":"No Content"},"404":{"description":"Not Found"}}}},"/schedules/{id}/doctor":{"get":{"tags":["schedule-property-reference-controller"],"description":"get-doctor-by-schedule-Id","operationId":"followPropertyReference-schedule-get_2_1","parameters":[{"name":"id","in":"path","required":true,"schema":{"type":"string"}}],"responses":{"200":{"description":"OK","content":{"application/hal+json":{"schema":{"$ref":"#/components/schemas/EntityModelDoctor"}},"text/uri-list":{"schema":{"type":"string"}}}},"404":{"description":"Not Found"}}},"put":{"tags":["schedule-property-reference-controller"],"description":"update-doctor-by-schedule-Id","operationId":"createPropertyReference-schedule-put_1","parameters":[{"name":"id","in":"path","required":true,"schema":{"type":"string"}}],"requestBody":{"content":{"application/json":{"schema":{"$ref":"#/components/schemas/CollectionModelObject"}},"application/x-spring-data-compact+json":{"schema":{"$ref":"#/components/schemas/CollectionModelObject"}},"text/uri-list":{"schema":{"type":"string"}}},"required":true},"responses":{"200":{"description":"OK","content":{"application/hal+json":{"schema":{"$ref":"#/components/schemas/EntityModelDoctor"}}}},"201":{"description":"Created","content":{"application/hal+json":{"schema":{"$ref":"#/components/schemas/EntityModelDoctor"}}}},"204":{"description":"No Content"}}},"delete":{"tags":["schedule-property-reference-controller"],"description":"delete-doctor-by-schedule-Id","operationId":"deletePropertyReference-schedule-delete_1","parameters":[{"name":"id","in":"path","required":true,"schema":{"type":"string"}}],"responses":{"204":{"description":"No Content"},"404":{"description":"Not Found"}}},"patch":{"tags":["schedule-property-reference-controller"],"description":"patch-doctor-by-schedule-Id","operationId":"createPropertyReference-schedule-patch_1","parameters":[{"name":"id","in":"path","required":true,"schema":{"type":"string"}}],"requestBody":{"content":{"application/json":{"schema":{"$ref":"#/components/schemas/CollectionModelObject"}},"application/x-spring-data-compact+json":{"schema":{"$ref":"#/components/schemas/CollectionModelObject"}},"text/uri-list":{"schema":{"type":"string"}}},"required":true},"responses":{"200":{"description":"OK","content":{"application/hal+json":{"schema":{"$ref":"#/components/schemas/EntityModelDoctor"}}}},"204":{"description":"No Content"}}}},"/schedules/{id}/doctor/{propertyId}":{"get":{"tags":["schedule-property-reference-controller"],"description":"get-doctor-by-schedule-Id","operationId":"followPropertyReference-schedule-get_2","parameters":[{"name":"id","in":"path","required":true,"schema":{"type":"string"}},{"name":"propertyId","in":"path","required":true,"schema":{"type":"string"}}],"responses":{"200":{"description":"OK","content":{"application/hal+json":{"schema":{"$ref":"#/components/schemas/EntityModelDoctor"}}}},"404":{"description":"Not Found"}}},"delete":{"tags":["schedule-property-reference-controller"],"description":"delete-doctor-by-schedule-Id","operationId":"deletePropertyReferenceId-schedule-delete_1","parameters":[{"name":"id","in":"path","required":true,"schema":{"type":"string"}},{"name":"propertyId","in":"path","required":true,"schema":{"type":"string"}}],"responses":{"204":{"description":"No Content"},"404":{"description":"Not Found"}}}},"/api/v1/responsaveis/{id}":{"get":{"tags":["Responsavel"],"operationId":"findBy","parameters":[{"name":"id","in":"path","required":true,"schema":{"type":"string","format":"uuid"}}],"responses":{"404":{"description":"Not Found","content":{"application/hal+json":{"schema":{"type":"object","additionalProperties":{"type":"string"}}}}},"400":{"description":"Bad Request","content":{"application/hal+json":{"schema":{"type":"object","additionalProperties":{"type":"string"}}}}},"422":{"description":"Unprocessable Entity","content":{"application/hal+json":{"schema":{"type":"object","additionalProperties":{"type":"string"}}}}},"500":{"description":"Internal Server Error","content":{"application/hal+json":{"schema":{"type":"object","additionalProperties":{"type":"string"}}}}},"405":{"description":"Method Not Allowed","content":{"application/hal+json":{"schema":{"type":"object","additionalProperties":{"type":"string"}}}}},"200":{"description":"OK","content":{"application/json":{"schema":{"$ref":"#/components/schemas/Responsavel"}}}}}},"put":{"tags":["Responsavel"],"operationId":"updateAll","parameters":[{"name":"id","in":"path","required":true,"schema":{"type":"string","format":"uuid"}}],"requestBody":{"content":{"application/json":{"schema":{"$ref":"#/components/schemas/Responsavel"}}},"required":true},"responses":{"404":{"description":"Not Found","content":{"application/hal+json":{"schema":{"type":"object","additionalProperties":{"type":"string"}}}}},"400":{"description":"Bad Request","content":{"application/hal+json":{"schema":{"type":"object","additionalProperties":{"type":"string"}}}}},"422":{"description":"Unprocessable Entity","content":{"application/hal+json":{"schema":{"type":"object","additionalProperties":{"type":"string"}}}}},"500":{"description":"Internal Server Error","content":{"application/hal+json":{"schema":{"type":"object","additionalProperties":{"type":"string"}}}}},"405":{"description":"Method Not Allowed","content":{"application/hal+json":{"schema":{"type":"object","additionalProperties":{"type":"string"}}}}},"200":{"description":"OK","content":{"application/json":{"schema":{"$ref":"#/components/schemas/Responsavel"}}}}}},"delete":{"tags":["Responsavel"],"operationId":"deleted","parameters":[{"name":"id","in":"path","required":true,"schema":{"type":"string","format":"uuid"}}],"responses":{"404":{"description":"Not Found","content":{"application/hal+json":{"schema":{"type":"object","additionalProperties":{"type":"string"}}}}},"400":{"description":"Bad Request","content":{"application/hal+json":{"schema":{"type":"object","additionalProperties":{"type":"string"}}}}},"422":{"description":"Unprocessable Entity","content":{"application/hal+json":{"schema":{"type":"object","additionalProperties":{"type":"string"}}}}},"500":{"description":"Internal Server Error","content":{"application/hal+json":{"schema":{"type":"object","additionalProperties":{"type":"string"}}}}},"405":{"description":"Method Not Allowed","content":{"application/hal+json":{"schema":{"type":"object","additionalProperties":{"type":"string"}}}}},"200":{"description":"OK","content":{"application/json":{"schema":{"type":"string"}}}}}}},"/api/v1/exames/{id}":{"get":{"tags":["Exam"],"operationId":"findByIdExame","parameters":[{"name":"id","in":"path","required":true,"schema":{"type":"string"}}],"responses":{"404":{"description":"Not Found","content":{"application/hal+json":{"schema":{"type":"object","additionalProperties":{"type":"string"}}}}},"400":{"description":"Bad Request","content":{"application/hal+json":{"schema":{"type":"object","additionalProperties":{"type":"string"}}}}},"422":{"description":"Unprocessable Entity","content":{"application/hal+json":{"schema":{"type":"object","additionalProperties":{"type":"string"}}}}},"500":{"description":"Internal Server Error","content":{"application/hal+json":{"schema":{"type":"object","additionalProperties":{"type":"string"}}}}},"405":{"description":"Method Not Allowed","content":{"application/hal+json":{"schema":{"type":"object","additionalProperties":{"type":"string"}}}}},"200":{"description":"OK","content":{"application/json":{"schema":{"$ref":"#/components/schemas/Exam"}}}}}},"put":{"tags":["Exam"],"operationId":"updateExame","parameters":[{"name":"id","in":"path","required":true,"schema":{"type":"string","format":"uuid"}}],"requestBody":{"content":{"application/json":{"schema":{"$ref":"#/components/schemas/ExamUpdateDTO"}}},"required":true},"responses":{"404":{"description":"Not Found","content":{"application/hal+json":{"schema":{"type":"object","additionalProperties":{"type":"string"}}}}},"400":{"description":"Bad Request","content":{"application/hal+json":{"schema":{"type":"object","additionalProperties":{"type":"string"}}}}},"422":{"description":"Unprocessable Entity","content":{"application/hal+json":{"schema":{"type":"object","additionalProperties":{"type":"string"}}}}},"500":{"description":"Internal Server Error","content":{"application/hal+json":{"schema":{"type":"object","additionalProperties":{"type":"string"}}}}},"405":{"description":"Method Not Allowed","content":{"application/hal+json":{"schema":{"type":"object","additionalProperties":{"type":"string"}}}}},"204":{"description":"No Content","content":{"application/json":{"schema":{"$ref":"#/components/schemas/Exam"}}}}}},"delete":{"tags":["Exam"],"operationId":"deleteExame","parameters":[{"name":"id","in":"path","required":true,"schema":{"type":"string","format":"uuid"}}],"responses":{"404":{"description":"Not Found","content":{"application/hal+json":{"schema":{"type":"object","additionalProperties":{"type":"string"}}}}},"400":{"description":"Bad Request","content":{"application/hal+json":{"schema":{"type":"object","additionalProperties":{"type":"string"}}}}},"422":{"description":"Unprocessable Entity","content":{"application/hal+json":{"schema":{"type":"object","additionalProperties":{"type":"string"}}}}},"500":{"description":"Internal Server Error","content":{"application/hal+json":{"schema":{"type":"object","additionalProperties":{"type":"string"}}}}},"405":{"description":"Method Not Allowed","content":{"application/hal+json":{"schema":{"type":"object","additionalProperties":{"type":"string"}}}}},"202":{"description":"Accepted","content":{"application/json":{"schema":{"type":"string"}}}}}}},"/api/v1/responsaveis":{"post":{"tags":["Responsavel"],"operationId":"create","requestBody":{"content":{"application/json":{"schema":{"$ref":"#/components/schemas/Responsavel"}}},"required":true},"responses":{"404":{"description":"Not Found","content":{"application/hal+json":{"schema":{"type":"object","additionalProperties":{"type":"string"}}}}},"400":{"description":"Bad Request","content":{"application/hal+json":{"schema":{"type":"object","additionalProperties":{"type":"string"}}}}},"422":{"description":"Unprocessable Entity","content":{"application/hal+json":{"schema":{"type":"object","additionalProperties":{"type":"string"}}}}},"500":{"description":"Internal Server Error","content":{"application/hal+json":{"schema":{"type":"object","additionalProperties":{"type":"string"}}}}},"405":{"description":"Method Not Allowed","content":{"application/hal+json":{"schema":{"type":"object","additionalProperties":{"type":"string"}}}}},"200":{"description":"OK","content":{"application/json":{"schema":{"$ref":"#/components/schemas/Responsavel"}}}}}}},"/api/v1/pacientes":{"get":{"tags":["Paciente"],"operationId":"findAll_1","responses":{"404":{"description":"Not Found","content":{"application/hal+json":{"schema":{"type":"object","additionalProperties":{"type":"string"}}}}},"400":{"description":"Bad Request","content":{"application/hal+json":{"schema":{"type":"object","additionalProperties":{"type":"string"}}}}},"422":{"description":"Unprocessable Entity","content":{"application/hal+json":{"schema":{"type":"object","additionalProperties":{"type":"string"}}}}},"500":{"description":"Internal Server Error","content":{"application/hal+json":{"schema":{"type":"object","additionalProperties":{"type":"string"}}}}},"405":{"description":"Method Not Allowed","content":{"application/hal+json":{"schema":{"type":"object","additionalProperties":{"type":"string"}}}}},"200":{"description":"OK","content":{"application/json":{"schema":{"type":"string"}}}}}},"post":{"tags":["Paciente"],"operationId":"save","requestBody":{"content":{"application/json":{"schema":{"$ref":"#/components/schemas/Paciente"}}},"required":true},"responses":{"404":{"description":"Not Found","content":{"application/hal+json":{"schema":{"type":"object","additionalProperties":{"type":"string"}}}}},"400":{"description":"Bad Request","content":{"application/hal+json":{"schema":{"type":"object","additionalProperties":{"type":"string"}}}}},"422":{"description":"Unprocessable Entity","content":{"application/hal+json":{"schema":{"type":"object","additionalProperties":{"type":"string"}}}}},"500":{"description":"Internal Server Error","content":{"application/hal+json":{"schema":{"type":"object","additionalProperties":{"type":"string"}}}}},"405":{"description":"Method Not Allowed","content":{"application/hal+json":{"schema":{"type":"object","additionalProperties":{"type":"string"}}}}},"200":{"description":"OK","content":{"application/json":{"schema":{"type":"string"}}}}}}},"/api/v1/exames":{"get":{"tags":["Exam"],"summary":"Busca dados de profissionais por idade e cargo exercido","operationId":"findAllExame","responses":{"404":{"description":"Not Found","content":{"application/hal+json":{"schema":{"type":"object","additionalProperties":{"type":"string"}}}}},"400":{"description":"Parametros inválidos","content":{"application/hal+json":{"schema":{"type":"object","additionalProperties":{"type":"string"}}}}},"422":{"description":"Dados de requisição inválida","content":{"application/hal+json":{"schema":{"type":"object","additionalProperties":{"type":"string"}}}}},"500":{"description":"Erro ao realizar busca dos dados","content":{"application/hal+json":{"schema":{"type":"object","additionalProperties":{"type":"string"}}}}},"405":{"description":"Method Not Allowed","content":{"application/hal+json":{"schema":{"type":"object","additionalProperties":{"type":"string"}}}}},"200":{"description":"Busca realizada com sucesso","content":{"application/json":{"schema":{"type":"array","items":{"$ref":"#/components/schemas/Exam"}}}}}}},"post":{"tags":["Exam"],"operationId":"createExame","requestBody":{"content":{"application/json":{"schema":{"$ref":"#/components/schemas/ExamDTO"}}},"required":true},"responses":{"404":{"description":"Not Found","content":{"application/hal+json":{"schema":{"type":"object","additionalProperties":{"type":"string"}}}}},"400":{"description":"Bad Request","content":{"application/hal+json":{"schema":{"type":"object","additionalProperties":{"type":"string"}}}}},"422":{"description":"Unprocessable Entity","content":{"application/hal+json":{"schema":{"type":"object","additionalProperties":{"type":"string"}}}}},"500":{"description":"Internal Server Error","content":{"application/hal+json":{"schema":{"type":"object","additionalProperties":{"type":"string"}}}}},"405":{"description":"Method Not Allowed","content":{"application/hal+json":{"schema":{"type":"object","additionalProperties":{"type":"string"}}}}},"201":{"description":"Created","content":{"application/json":{"schema":{"$ref":"#/components/schemas/Exam"}}}}}}},"/api/v1/consultas":{"get":{"tags":["Consulta"],"operationId":"pegaTodasConsulta","responses":{"404":{"description":"Not Found","content":{"application/hal+json":{"schema":{"type":"object","additionalProperties":{"type":"string"}}}}},"400":{"description":"Bad Request","content":{"application/hal+json":{"schema":{"type":"object","additionalProperties":{"type":"string"}}}}},"422":{"description":"Unprocessable Entity","content":{"application/hal+json":{"schema":{"type":"object","additionalProperties":{"type":"string"}}}}},"500":{"description":"Internal Server Error","content":{"application/hal+json":{"schema":{"type":"object","additionalProperties":{"type":"string"}}}}},"405":{"description":"Method Not Allowed","content":{"application/hal+json":{"schema":{"type":"object","additionalProperties":{"type":"string"}}}}},"200":{"description":"OK","content":{"application/json":{"schema":{"type":"array","items":{"$ref":"#/components/schemas/Consulta"}}}}}}},"post":{"tags":["Consulta"],"operationId":"salvaConsulta","requestBody":{"content":{"application/json":{"schema":{"$ref":"#/components/schemas/Consulta"}}},"required":true},"responses":{"404":{"description":"Not Found","content":{"application/hal+json":{"schema":{"type":"object","additionalProperties":{"type":"string"}}}}},"400":{"description":"Bad Request","content":{"application/hal+json":{"schema":{"type":"object","additionalProperties":{"type":"string"}}}}},"422":{"description":"Unprocessable Entity","content":{"application/hal+json":{"schema":{"type":"object","additionalProperties":{"type":"string"}}}}},"500":{"description":"Internal Server Error","content":{"application/hal+json":{"schema":{"type":"object","additionalProperties":{"type":"string"}}}}},"405":{"description":"Method Not Allowed","content":{"application/hal+json":{"schema":{"type":"object","additionalProperties":{"type":"string"}}}}},"200":{"description":"OK","content":{"application/json":{"schema":{"$ref":"#/components/schemas/Consulta"}}}}}}},"/schedules/":{"get":{"tags":["Schedule"],"summary":"Busca dados de profissionais por idade e cargo exercido","operationId":"findAllAgenda","responses":{"404":{"description":"Not Found","content":{"application/hal+json":{"schema":{"type":"object","additionalProperties":{"type":"string"}}}}},"400":{"description":"Parametros inválidos","content":{"application/hal+json":{"schema":{"type":"object","additionalProperties":{"type":"string"}}}}},"422":{"description":"Dados de requisição inválida","content":{"application/hal+json":{"schema":{"type":"object","additionalProperties":{"type":"string"}}}}},"500":{"description":"Erro ao realizar busca dos dados","content":{"application/hal+json":{"schema":{"type":"object","additionalProperties":{"type":"string"}}}}},"405":{"description":"Method Not Allowed","content":{"application/hal+json":{"schema":{"type":"object","additionalProperties":{"type":"string"}}}}},"200":{"description":"Busca realizada com sucesso","content":{"application/json":{"schema":{"type":"array","items":{"$ref":"#/components/schemas/Schedule"}}}}}}}},"/api/v1/responsaveis/":{"get":{"tags":["Responsavel"],"operationId":"findAll","responses":{"404":{"description":"Not Found","content":{"application/hal+json":{"schema":{"type":"object","additionalProperties":{"type":"string"}}}}},"400":{"description":"Bad Request","content":{"application/hal+json":{"schema":{"type":"object","additionalProperties":{"type":"string"}}}}},"422":{"description":"Unprocessable Entity","content":{"application/hal+json":{"schema":{"type":"object","additionalProperties":{"type":"string"}}}}},"500":{"description":"Internal Server Error","content":{"application/hal+json":{"schema":{"type":"object","additionalProperties":{"type":"string"}}}}},"405":{"description":"Method Not Allowed","content":{"application/hal+json":{"schema":{"type":"object","additionalProperties":{"type":"string"}}}}},"200":{"description":"OK","content":{"application/json":{"schema":{"type":"array","items":{"$ref":"#/components/schemas/Responsavel"}}}}}}}},"/api/v1/pacientes/{id}":{"get":{"tags":["Paciente"],"operationId":"find","parameters":[{"name":"id","in":"path","required":true,"schema":{"type":"string"}}],"responses":{"404":{"description":"Not Found","content":{"application/hal+json":{"schema":{"type":"object","additionalProperties":{"type":"string"}}}}},"400":{"description":"Bad Request","content":{"application/hal+json":{"schema":{"type":"object","additionalProperties":{"type":"string"}}}}},"422":{"description":"Unprocessable Entity","content":{"application/hal+json":{"schema":{"type":"object","additionalProperties":{"type":"string"}}}}},"500":{"description":"Internal Server Error","content":{"application/hal+json":{"schema":{"type":"object","additionalProperties":{"type":"string"}}}}},"405":{"description":"Method Not Allowed","content":{"application/hal+json":{"schema":{"type":"object","additionalProperties":{"type":"string"}}}}},"200":{"description":"OK","content":{"application/json":{"schema":{"type":"string"}}}}}},"delete":{"tags":["Paciente"],"operationId":"delete","parameters":[{"name":"id","in":"path","required":true,"schema":{"type":"string"}}],"responses":{"404":{"description":"Not Found","content":{"application/hal+json":{"schema":{"type":"object","additionalProperties":{"type":"string"}}}}},"400":{"description":"Bad Request","content":{"application/hal+json":{"schema":{"type":"object","additionalProperties":{"type":"string"}}}}},"422":{"description":"Unprocessable Entity","content":{"application/hal+json":{"schema":{"type":"object","additionalProperties":{"type":"string"}}}}},"500":{"description":"Internal Server Error","content":{"application/hal+json":{"schema":{"type":"object","additionalProperties":{"type":"string"}}}}},"405":{"description":"Method Not Allowed","content":{"application/hal+json":{"schema":{"type":"object","additionalProperties":{"type":"string"}}}}},"200":{"description":"OK","content":{"application/json":{"schema":{"type":"string"}}}}}}},"/api/v1/consultas/{id}":{"get":{"tags":["Consulta"],"operationId":"getConsultaOne","responses":{"404":{"description":"Not Found","content":{"application/hal+json":{"schema":{"type":"object","additionalProperties":{"type":"string"}}}}},"400":{"description":"Bad Request","content":{"application/hal+json":{"schema":{"type":"object","additionalProperties":{"type":"string"}}}}},"422":{"description":"Unprocessable Entity","content":{"application/hal+json":{"schema":{"type":"object","additionalProperties":{"type":"string"}}}}},"500":{"description":"Internal Server Error","content":{"application/hal+json":{"schema":{"type":"object","additionalProperties":{"type":"string"}}}}},"405":{"description":"Method Not Allowed","content":{"application/hal+json":{"schema":{"type":"object","additionalProperties":{"type":"string"}}}}},"200":{"description":"OK","content":{"application/json":{"schema":{"$ref":"#/components/schemas/Consulta"}}}}}}}},"components":{"schemas":{"AbstractJsonSchemaPropertyObject":{"type":"object","properties":{"title":{"type":"string"},"readOnly":{"type":"boolean"}}},"Item":{"type":"object","properties":{"type":{"type":"string"},"properties":{"type":"object","additionalProperties":{"$ref":"#/components/schemas/AbstractJsonSchemaPropertyObject"}},"requiredProperties":{"type":"array","items":{"type":"string"}}}},"JsonSchema":{"type":"object","properties":{"title":{"type":"string"},"description":{"type":"string"},"properties":{"type":"object","additionalProperties":{"$ref":"#/components/schemas/AbstractJsonSchemaPropertyObject"}},"requiredProperties":{"type":"array","items":{"type":"string"}},"definitions":{"type":"object","additionalProperties":{"$ref":"#/components/schemas/Item"}},"type":{"type":"string"},"$schema":{"type":"string"}}},"Links":{"type":"object","additionalProperties":{"$ref":"#/components/schemas/Link"}},"RepresentationModelObject":{"type":"object","properties":{"_links":{"$ref":"#/components/schemas/Links"}}},"Paciente":{"type":"object","properties":{"id":{"type":"string","format":"uuid"},"nome":{"type":"string"},"dataNascimento":{"type":"string","format":"date-time"},"rg":{"type":"string"},"cpf":{"type":"string"},"sexoBiologico":{"type":"string"}}},"EntityModelPaciente":{"type":"object","properties":{"nome":{"type":"string"},"dataNascimento":{"type":"string","format":"date-time"},"rg":{"type":"string"},"cpf":{"type":"string"},"sexoBiologico":{"type":"string"},"_links":{"$ref":"#/components/schemas/Links"}}},"PageMetadata":{"type":"object","properties":{"size":{"type":"integer","format":"int64"},"totalElements":{"type":"integer","format":"int64"},"totalPages":{"type":"integer","format":"int64"},"number":{"type":"integer","format":"int64"}}},"PagedModelEntityModelPaciente":{"type":"object","properties":{"_embedded":{"type":"object","properties":{"pacientes":{"type":"array","items":{"$ref":"#/components/schemas/EntityModelPaciente"}}}},"_links":{"$ref":"#/components/schemas/Links"},"page":{"$ref":"#/components/schemas/PageMetadata"}}},"Responsavel":{"type":"object","properties":{"id":{"type":"string","format":"uuid"},"nome":{"type":"string"},"sobrenome":{"type":"string"},"dataNascimento":{"type":"string","format":"date-time"},"vinculo":{"type":"string","enum":["PAI","MAE","IRMAO","TIO","AVO","TIA","IRMA","PRIMO","VIZINHO","PADASTRO","MADRASTRA","OUTROS"]}}},"EntityModelResponsavel":{"type":"object","properties":{"nome":{"type":"string"},"sobrenome":{"type":"string"},"dataNascimento":{"type":"string","format":"date-time"},"vinculo":{"type":"string","enum":["PAI","MAE","IRMAO","TIO","AVO","TIA","IRMA","PRIMO","VIZINHO","PADASTRO","MADRASTRA","OUTROS"]},"_links":{"$ref":"#/components/schemas/Links"}}},"PagedModelEntityModelResponsavel":{"type":"object","properties":{"_embedded":{"type":"object","properties":{"responsavels":{"type":"array","items":{"$ref":"#/components/schemas/EntityModelResponsavel"}}}},"_links":{"$ref":"#/components/schemas/Links"},"page":{"$ref":"#/components/schemas/PageMetadata"}}},"Consulta":{"type":"object","properties":{"id":{"type":"string","format":"uuid"},"diaConsulta":{"type":"string","format":"date-time"},"horaConsulta":{"type":"string"},"medicoId":{"type":"string"},"exameId":{"type":"string"},"pacienteId":{"type":"string"}}},"Doctor":{"type":"object","properties":{"id":{"type":"string","format":"uuid"},"nome":{"type":"string"},"sobrenome":{"type":"string"},"crm":{"type":"string"},"rg":{"type":"string"},"cpf":{"type":"string"},"schedules":{"type":"array","items":{"$ref":"#/components/schemas/Schedule"}}}},"Schedule":{"type":"object","properties":{"id":{"type":"string","format":"uuid"},"doctor":{"$ref":"#/components/schemas/Doctor"},"consulta":{"$ref":"#/components/schemas/Consulta"}}},"EntityModelDoctor":{"type":"object","properties":{"nome":{"type":"string"},"sobrenome":{"type":"string"},"crm":{"type":"string"},"rg":{"type":"string"},"cpf":{"type":"string"},"_links":{"$ref":"#/components/schemas/Links"}}},"PagedModelEntityModelDoctor":{"type":"object","properties":{"_embedded":{"type":"object","properties":{"doctors":{"type":"array","items":{"$ref":"#/components/schemas/EntityModelDoctor"}}}},"_links":{"$ref":"#/components/schemas/Links"},"page":{"$ref":"#/components/schemas/PageMetadata"}}},"CollectionModelSchedule":{"type":"object","properties":{"_embedded":{"type":"object","properties":{"schedules":{"type":"array","items":{"$ref":"#/components/schemas/ScheduleResponse"}}}},"_links":{"$ref":"#/components/schemas/Links"}}},"CollectionModelObject":{"type":"object","properties":{"_embedded":{"type":"object","properties":{"objects":{"type":"array","items":{"type":"object"}}}},"_links":{"$ref":"#/components/schemas/Links"}}},"EntityModelSchedule":{"type":"object","properties":{"_links":{"$ref":"#/components/schemas/Links"}}},"PagedModelEntityModelSchedule":{"type":"object","properties":{"_embedded":{"type":"object","properties":{"schedules":{"type":"array","items":{"$ref":"#/components/schemas/EntityModelSchedule"}}}},"_links":{"$ref":"#/components/schemas/Links"},"page":{"$ref":"#/components/schemas/PageMetadata"}}},"EntityModelConsulta":{"type":"object","properties":{"diaConsulta":{"type":"string","format":"date-time"},"horaConsulta":{"type":"string"},"medicoId":{"type":"string"},"exameId":{"type":"string"},"pacienteId":{"type":"string"},"_links":{"$ref":"#/components/schemas/Links"}}},"Exam":{"required":["descricaoCurta","descricaoLonga","nome"],"type":"object","properties":{"id":{"type":"string","format":"uuid"},"nome":{"type":"string"},"descricaoCurta":{"type":"string"},"descricaoLonga":{"type":"string"}}},"EntityModelExam":{"required":["descricaoCurta","descricaoLonga","nome"],"type":"object","properties":{"nome":{"type":"string"},"descricaoCurta":{"type":"string"},"descricaoLonga":{"type":"string"},"_links":{"$ref":"#/components/schemas/Links"}}},"PagedModelEntityModelExam":{"type":"object","properties":{"_embedded":{"type":"object","properties":{"exams":{"type":"array","items":{"$ref":"#/components/schemas/EntityModelExam"}}}},"_links":{"$ref":"#/components/schemas/Links"},"page":{"$ref":"#/components/schemas/PageMetadata"}}},"PagedModelEntityModelConsulta":{"type":"object","properties":{"_embedded":{"type":"object","properties":{"consultas":{"type":"array","items":{"$ref":"#/components/schemas/EntityModelConsulta"}}}},"_links":{"$ref":"#/components/schemas/Links"},"page":{"$ref":"#/components/schemas/PageMetadata"}}},"ConsultaRequestBody":{"type":"object","properties":{"id":{"type":"string","format":"uuid"},"diaConsulta":{"type":"string","format":"date-time"},"horaConsulta":{"type":"string"},"medicoId":{"type":"string"},"exameId":{"type":"string"},"pacienteId":{"type":"string"}}},"DoctorRequestBody":{"type":"object","properties":{"id":{"type":"string","format":"uuid"},"nome":{"type":"string"},"sobrenome":{"type":"string"},"crm":{"type":"string"},"rg":{"type":"string"},"cpf":{"type":"string"},"schedules":{"type":"array","items":{"type":"string"}}}},"ScheduleRequestBody":{"type":"object","properties":{"id":{"type":"string","format":"uuid"},"doctor":{"type":"string"},"consulta":{"type":"string"}}},"ScheduleResponse":{"type":"object","properties":{}},"ExamRequestBody":{"required":["descricaoCurta","descricaoLonga","nome"],"type":"object","properties":{"id":{"type":"string","format":"uuid"},"nome":{"type":"string"},"descricaoCurta":{"type":"string"},"descricaoLonga":{"type":"string"}}},"PacienteRequestBody":{"type":"object","properties":{"id":{"type":"string","format":"uuid"},"nome":{"type":"string"},"dataNascimento":{"type":"string","format":"date-time"},"rg":{"type":"string"},"cpf":{"type":"string"},"sexoBiologico":{"type":"string"}}},"ResponsavelRequestBody":{"type":"object","properties":{"id":{"type":"string","format":"uuid"},"nome":{"type":"string"},"sobrenome":{"type":"string"},"dataNascimento":{"type":"string","format":"date-time"},"vinculo":{"type":"string","enum":["PAI","MAE","IRMAO","TIO","AVO","TIA","IRMA","PRIMO","VIZINHO","PADASTRO","MADRASTRA","OUTROS"]}}},"ExamUpdateDTO":{"required":["descricaoCurta","descricaoLonga","nome"],"type":"object","properties":{"nome":{"type":"string"},"descricaoCurta":{"type":"string"},"descricaoLonga":{"type":"string"}}},"ExamDTO":{"required":["descricao curta","descricao longa","nome"],"type":"object","properties":{"nome":{"type":"string"},"descricao curta":{"type":"string"},"descricao longa":{"type":"string"}}},"Link":{"type":"object","properties":{"href":{"type":"string"},"hreflang":{"type":"string"},"title":{"type":"string"},"type":{"type":"string"},"deprecation":{"type":"string"},"profile":{"type":"string"},"name":{"type":"string"},"templated":{"type":"boolean"}}}}}}